django_delta_logger/__init__.py
django_delta_logger/apps.py
django_delta_logger/delta_logger.py
django_delta_logger/fields.py
django_delta_logger/models.py
django_delta_logger/serializers.py
django_delta_logger/settings.py
django_delta_logger/migrations/0001_initial.py
django_delta_logger/migrations/__init__.py
django_delta_logger-0.1.1.dist-info/LICENSE
django_delta_logger-0.1.1.dist-info/METADATA
django_delta_logger-0.1.1.dist-info/WHEEL
django_delta_logger-0.1.1.dist-info/top_level.txt
django_delta_logger-0.1.1.dist-info/RECORD
