Metadata-Version: 2.1
Name: django-delta-logger
Version: 0.1.1
Summary: Model instance change logging for django models.
Home-page: UNKNOWN
Author: Tanner Netterville
Author-email: tannern@gmail.com
License: UNKNOWN
Platform: UNKNOWN
Classifier: Programming Language :: Python :: 3
Classifier: License :: OSI Approved :: MIT License
Classifier: Operating System :: OS Independent
Requires-Dist: django (>=2.2)
